dusseldorf/__init__.py
dusseldorf/dusseldorf.py
dusseldorf/exceptions.py
dusseldorf/models.py
dusseldorf/py.typed
dusseldorf-1.0.0.dist-info/LICENSE
dusseldorf-1.0.0.dist-info/METADATA
dusseldorf-1.0.0.dist-info/WHEEL
dusseldorf-1.0.0.dist-info/RECORD
